{
  "timeZone": "Asia/Tokyo",
  "dependencies": {
    "enabledAdvancedServices": [{
      "userSymbol": "Drive",
      "serviceId": "drive",
      "version": "v2"
    }],
    "libraries": [{
      "userSymbol": "Str",
      "libraryId": "13sX98YHiFh-5eBWTAJtWR52SbdnCxaHzX3GXgt8zUU07ELz9ArLhlJvD",
      "version": "10",
      "developmentMode": true
    }, {
      "userSymbol": "Is",
      "libraryId": "1ovfzNY0BUREXY5Ky0eX1HZaz3VxEoq3wyjwZuYg4L6m8H83Rjb8Q1yhw",
      "version": "10",
      "developmentMode": true
    }, {
      "userSymbol": "Assert",
      "libraryId": "10lJqYuurUoouFS-aPsPs4HU2s--Xkm5vTu7QVZH4HwcAZgtCDU6ZltQN",
      "version": "27",
      "developmentMode": true
    }]
  },
  "webapp": {
    "access": "ANYONE",
    "executeAs": "USER_ACCESSING"
  },
  "exceptionLogging": "STACKDRIVER",
  "runtimeVersion": "V8"
}